text2xl/__init__.py
text2xl/__main__.py
text2xl-0.0.0.dev0.dist-info/LICENSE.md
text2xl-0.0.0.dev0.dist-info/METADATA
text2xl-0.0.0.dev0.dist-info/WHEEL
text2xl-0.0.0.dev0.dist-info/top_level.txt
text2xl-0.0.0.dev0.dist-info/RECORD
