Metadata-Version: 2.1
Name: text2xl
Version: 0.0.0.dev0
Summary: Text Data to Excel Converter
Home-page: https://github.com/baxterda/text2xl
Author: Dawson Baxter
Author-email: dbaxtersoftware@gmail.com
License: MIT
Platform: UNKNOWN
Classifier: License :: OSI Approved :: MIT License
Requires-Python: >=3.6
License-File: LICENSE.md
Requires-Dist: xlsxwriter
